redisGroupMsg/ME.py
redisGroupMsg/__init__.py
redisGroupMsg/lib.py
redisGroupMsg-0.0.5.dist-info/METADATA
redisGroupMsg-0.0.5.dist-info/WHEEL
redisGroupMsg-0.0.5.dist-info/top_level.txt
redisGroupMsg-0.0.5.dist-info/RECORD
