Metadata-Version: 2.1
Name: redisGroupMsg
Version: 0.0.5
Summary: This is a packet that broadcasts redis multiple queues
Home-page: https://github.com/zhenruyan/redisGroupMsg
Author: zhenruyan
Author-email: baiyangwangzhan@hotmail.com
License: WTFPL
Platform: all
Classifier: Operating System :: OS Independent
Classifier: Intended Audience :: Developers
Classifier: Programming Language :: Python :: 3.5
Classifier: Programming Language :: Python :: 3.6
Classifier: Programming Language :: Python :: 3.7
Classifier: Topic :: Software Development :: Libraries
Requires-Dist: redis (==3.0.1)
